ragbits/evaluate/__init__.py
ragbits/evaluate/cli.py
ragbits/evaluate/config.py
ragbits/evaluate/evaluator.py
ragbits/evaluate/optimizer.py
ragbits/evaluate/py.typed
ragbits/evaluate/utils.py
ragbits/evaluate/dataloaders/__init__.py
ragbits/evaluate/dataloaders/base.py
ragbits/evaluate/dataloaders/document_search.py
ragbits/evaluate/dataloaders/exceptions.py
ragbits/evaluate/dataloaders/question_answer.py
ragbits/evaluate/dataset_generator/__init__.py
ragbits/evaluate/dataset_generator/pipeline.py
ragbits/evaluate/dataset_generator/utils.py
ragbits/evaluate/dataset_generator/prompts/__init__.py
ragbits/evaluate/dataset_generator/prompts/corpus_generation.py
ragbits/evaluate/dataset_generator/prompts/qa.py
ragbits/evaluate/dataset_generator/tasks/__init__.py
ragbits/evaluate/dataset_generator/tasks/corpus_generation.py
ragbits/evaluate/dataset_generator/tasks/filter/__init__.py
ragbits/evaluate/dataset_generator/tasks/filter/base.py
ragbits/evaluate/dataset_generator/tasks/filter/dont_know.py
ragbits/evaluate/dataset_generator/tasks/text_generation/__init__.py
ragbits/evaluate/dataset_generator/tasks/text_generation/base.py
ragbits/evaluate/dataset_generator/tasks/text_generation/qa.py
ragbits/evaluate/factories/__init__.py
ragbits/evaluate/metrics/__init__.py
ragbits/evaluate/metrics/base.py
ragbits/evaluate/metrics/document_search.py
ragbits/evaluate/metrics/question_answer.py
ragbits/evaluate/pipelines/__init__.py
ragbits/evaluate/pipelines/base.py
ragbits/evaluate/pipelines/document_search.py
ragbits/evaluate/pipelines/question_answer.py
ragbits_evaluate-1.3.0.dist-info/METADATA
ragbits_evaluate-1.3.0.dist-info/WHEEL
ragbits_evaluate-1.3.0.dist-info/RECORD
